{
  "id": "cluster-v1",
  "title": "Cluster",
  "categories": [
    {
      "id": "world-capitals",
      "name": "World Capitals",
      "items": [
        "London",
        "Paris",
        "Berlin",
        "Rome",
        "Madrid",
        "Lisbon",
        "Amsterdam",
        "Brussels",
        "Vienna",
        "Warsaw",
        "Prague",
        "Budapest",
        "Athens",
        "Stockholm",
        "Oslo",
        "Copenhagen",
        "Helsinki",
        "Dublin",
        "Ottawa",
        "Washington D.C.",
        "Mexico City",
        "Havana",
        "Bogotá",
        "Lima",
        "Buenos Aires",
        "Santiago",
        "Brasília",
        "Tokyo",
        "Beijing",
        "Seoul",
        "New Delhi",
        "Bangkok",
        "Jakarta",
        "Manila",
        "Cairo",
        "Nairobi",
        "Lagos",
        "Accra",
        "Addis Ababa",
        "Canberra",
        "Islamabad",
        "Ankara",
        "Riyadh",
        "Tehran",
        "Baghdad"
      ]
    },
    {
      "id": "us-national-parks",
      "name": "U.S. National Parks",
      "items": [
        "Yellowstone",
        "Yosemite",
        "Grand Canyon",
        "Zion",
        "Bryce Canyon",
        "Arches",
        "Canyonlands",
        "Capitol Reef",
        "Rocky Mountain",
        "Great Smoky Mountains",
        "Acadia",
        "Olympic",
        "Mount Rainier",
        "North Cascades",
        "Crater Lake",
        "Redwood",
        "Sequoia",
        "Kings Canyon",
        "Joshua Tree",
        "Death Valley",
        "Saguaro",
        "Petrified Forest",
        "Grand Teton",
        "Glacier",
        "Badlands",
        "Theodore Roosevelt",
        "Wind Cave",
        "Hot Springs",
        "Mammoth Cave",
        "Everglades",
        "Biscayne",
        "Dry Tortugas",
        "Shenandoah",
        "New River Gorge",
        "Cuyahoga Valley",
        "Indiana Dunes",
        "Isle Royale",
        "Voyageurs",
        "Kenai Fjords",
        "Denali",
        "Wrangell-St. Elias",
        "Katmai",
        "Haleakalā",
        "Hawaiʻi Volcanoes",
        "Mesa Verde"
      ]
    },
    {
      "id": "rivers-of-the-world",
      "name": "Rivers of the World",
      "items": [
        "Amazon",
        "Nile",
        "Mississippi",
        "Missouri",
        "Colorado",
        "Columbia",
        "Rio Grande",
        "Hudson",
        "Ohio",
        "Tennessee",
        "Yangtze",
        "Yellow River",
        "Mekong",
        "Ganges",
        "Indus",
        "Brahmaputra",
        "Tigris",
        "Euphrates",
        "Jordan",
        "Volga",
        "Danube",
        "Rhine",
        "Thames",
        "Seine",
        "Loire",
        "Po",
        "Tagus",
        "Ebro",
        "Congo",
        "Niger",
        "Zambezi",
        "Orange",
        "Limpopo",
        "Orinoco",
        "Paraná",
        "São Francisco",
        "Mackenzie",
        "Yukon",
        "Murray",
        "Irrawaddy",
        "Ob",
        "Yenisei",
        "Lena",
        "Amur",
        "Dnieper"
      ]
    },
    {
      "id": "islands",
      "name": "Islands",
      "items": [
        "Greenland",
        "Borneo",
        "Madagascar",
        "Sumatra",
        "Honshu",
        "Great Britain",
        "Iceland",
        "Ireland",
        "Hokkaido",
        "Hispaniola",
        "Sri Lanka",
        "Tasmania",
        "Cuba",
        "Newfoundland",
        "Sicily",
        "Sardinia",
        "Corsica",
        "Cyprus",
        "Malta",
        "Crete",
        "Majorca",
        "Tenerife",
        "Maui",
        "Oahu",
        "Kauai",
        "Trinidad",
        "Jamaica",
        "Puerto Rico",
        "Bali",
        "Fiji",
        "Maldives",
        "Ibiza",
        "Capri",
        "Santorini",
        "Zanzibar",
        "Mauritius",
        "Seychelles",
        "Réunion",
        "Galápagos",
        "Easter Island",
        "Tahiti",
        "Guam",
        "Luzon",
        "Java",
        "Mindanao"
      ]
    },
    {
      "id": "mountain-ranges",
      "name": "Mountain Ranges",
      "items": [
        "Himalayas",
        "Andes",
        "Alps",
        "Rockies",
        "Appalachians",
        "Urals",
        "Caucasus",
        "Atlas",
        "Pyrenees",
        "Carpathians",
        "Sierra Nevada",
        "Cascades",
        "Alaska Range",
        "Tian Shan",
        "Karakoram",
        "Hindu Kush",
        "Pamir",
        "Zagros",
        "Elburz",
        "Western Ghats",
        "Eastern Ghats",
        "Kunlun",
        "Altai",
        "Dolomites",
        "Apennines",
        "Balkans",
        "Tatras",
        "Black Forest",
        "Vosges",
        "Jura",
        "Pennines",
        "Cairngorms",
        "Scandinavian Mountains",
        "Great Dividing Range",
        "Drakensberg",
        "Ethiopian Highlands",
        "Brooks Range",
        "Ozarks",
        "Blue Ridge",
        "Adirondacks",
        "White Mountains",
        "Green Mountains",
        "Catskills",
        "Ozark Plateau",
        "Aravalli"
      ]
    },
    {
      "id": "chicken-breeds",
      "name": "Chicken Breeds",
      "items": [
        "Rhode Island Red",
        "Leghorn",
        "Plymouth Rock",
        "Sussex",
        "Orpington",
        "Wyandotte",
        "New Hampshire Red",
        "Australorp",
        "Brahma",
        "Cochin",
        "Silkie",
        "Polish",
        "Marans",
        "Welsummer",
        "Ameraucana",
        "Araucana",
        "Easter Egger",
        "Dominique",
        "Appenzeller",
        "Buckeye",
        "Delaware",
        "Jersey Giant",
        "Langshan",
        "Minorca",
        "Ancona",
        "Hamburg",
        "Faverolles",
        "Houdan",
        "Dorking",
        "Cornish",
        "Sebright",
        "Old English Game",
        "Modern Game",
        "Asil",
        "Shamo",
        "Cubalaya",
        "Catalana",
        "Yokohama",
        "Lakenvelder",
        "Campine",
        "Barnevelder",
        "Iowa Blue",
        "Turken",
        "Crevecoeur",
        "La Flèche"
      ]
    },
    {
      "id": "constellations",
      "name": "Constellations",
      "items": [
        "Orion",
        "Ursa Major",
        "Ursa Minor",
        "Cassiopeia",
        "Perseus",
        "Andromeda",
        "Pegasus",
        "Aquila",
        "Cygnus",
        "Leo",
        "Virgo",
        "Scorpius",
        "Sagittarius",
        "Capricornus",
        "Aquarius",
        "Pisces",
        "Aries",
        "Taurus",
        "Gemini",
        "Cancer",
        "Libra",
        "Draco",
        "Hercules",
        "Lyra",
        "Boötes",
        "Corona Borealis",
        "Ophiuchus",
        "Hydra",
        "Centaurus",
        "Lupus",
        "Corvus",
        "Crater",
        "Vela",
        "Canis Major",
        "Canis Minor",
        "Monoceros",
        "Eridanus",
        "Phoenix",
        "Cetus",
        "Lepus",
        "Columba",
        "Puppis",
        "Carina",
        "Piscis Austrinus",
        "Triangulum"
      ]
    },
    {
      "id": "dinosaurs",
      "name": "Dinosaurs",
      "items": [
        "Tyrannosaurus",
        "Velociraptor",
        "Triceratops",
        "Stegosaurus",
        "Brachiosaurus",
        "Diplodocus",
        "Ankylosaurus",
        "Spinosaurus",
        "Allosaurus",
        "Iguanodon",
        "Parasaurolophus",
        "Pachycephalosaurus",
        "Gallimimus",
        "Apatosaurus",
        "Carnotaurus",
        "Dilophosaurus",
        "Ceratosaurus",
        "Edmontosaurus",
        "Corythosaurus",
        "Maiasaura",
        "Oviraptor",
        "Deinonychus",
        "Utahraptor",
        "Therizinosaurus",
        "Giganotosaurus",
        "Carcharodontosaurus",
        "Argentinosaurus",
        "Euoplocephalus",
        "Styracosaurus",
        "Pentaceratops",
        "Protoceratops",
        "Psittacosaurus",
        "Heterodontosaurus",
        "Compsognathus",
        "Archaeopteryx",
        "Plateosaurus",
        "Coelophysis",
        "Herrerasaurus",
        "Baryonyx",
        "Suchomimus",
        "Irritator",
        "Kentrosaurus",
        "Sauropelta",
        "Nodosaurus",
        "Pteranodon"
      ]
    },
    {
      "id": "phobias",
      "name": "Phobias",
      "items": [
        "Arachnophobia",
        "Acrophobia",
        "Claustrophobia",
        "Agoraphobia",
        "Hydrophobia",
        "Nyctophobia",
        "Pyrophobia",
        "Cynophobia",
        "Ophidiophobia",
        "Entomophobia",
        "Trypanophobia",
        "Aerophobia",
        "Mysophobia",
        "Hemophobia",
        "Thanatophobia",
        "Glossophobia",
        "Coulrophobia",
        "Trypophobia",
        "Ailurophobia",
        "Ornithophobia",
        "Thalassophobia",
        "Phonophobia",
        "Scopophobia",
        "Nomophobia",
        "Catoptrophobia",
        "Somniphobia",
        "Arithmophobia",
        "Bibliophobia",
        "Iatrophobia",
        "Philophobia",
        "Katsaridaphobia",
        "Lepidopterophobia",
        "Selachophobia",
        "Batrachophobia",
        "Musophobia",
        "Hippopotomonstrosesquippedaliophobia",
        "Phasmophobia",
        "Automatonophobia",
        "Xenophobia",
        "Atychiphobia",
        "Decidophobia",
        "Ergophobia",
        "Gamophobia",
        "Heliophobia",
        "Isolophobia"
      ]
    },
    {
      "id": "bones-of-the-human-body",
      "name": "Bones of the Human Body",
      "items": [
        "Femur",
        "Tibia",
        "Fibula",
        "Patella",
        "Humerus",
        "Radius",
        "Ulna",
        "Scapula",
        "Clavicle",
        "Sternum",
        "Sacrum",
        "Coccyx",
        "Ilium",
        "Ischium",
        "Pubis",
        "Skull",
        "Mandible",
        "Maxilla",
        "Zygomatic",
        "Nasal Bone",
        "Frontal Bone",
        "Parietal Bone",
        "Occipital Bone",
        "Temporal Bone",
        "Sphenoid",
        "Ethmoid",
        "Incus",
        "Malleus",
        "Stapes",
        "Calcaneus",
        "Talus",
        "Navicular",
        "Cuboid",
        "Cuneiform",
        "Metatarsal",
        "Phalanx",
        "Carpals",
        "Metacarpals",
        "Ribs",
        "Hyoid",
        "Vomer",
        "Palatine",
        "Lacrimal",
        "Vertebra",
        "Pisiform"
      ]
    },
    {
      "id": "types-of-clouds",
      "name": "Types of Clouds",
      "items": [
        "Cumulus",
        "Stratus",
        "Cirrus",
        "Nimbostratus",
        "Cumulonimbus",
        "Stratocumulus",
        "Altocumulus",
        "Altostratus",
        "Cirrostratus",
        "Cirrocumulus",
        "Lenticular",
        "Mammatus",
        "Kelvin-Helmholtz",
        "Pileus",
        "Arcus",
        "Shelf Cloud",
        "Wall Cloud",
        "Virga",
        "Fog",
        "Noctilucent",
        "Nacreous",
        "Pyrocumulus",
        "Fractus",
        "Castellanus",
        "Fibratus",
        "Spissatus",
        "Floccus",
        "Radiatus",
        "Undulatus",
        "Lacunosus",
        "Asperitas",
        "Fluctus",
        "Volutus",
        "Cavum",
        "Fumulus",
        "Velum",
        "Pannus",
        "Praecipitatio",
        "Murus",
        "Cauda",
        "Intortus",
        "Vertebratus",
        "Duplicatus",
        "Translucidus",
        "Opacus"
      ]
    },
    {
      "id": "skin-conditions",
      "name": "Skin Conditions / Diseases",
      "items": [
        "Acne",
        "Eczema",
        "Psoriasis",
        "Rosacea",
        "Vitiligo",
        "Melanoma",
        "Hives",
        "Dermatitis",
        "Ringworm",
        "Impetigo",
        "Cellulitis",
        "Shingles",
        "Cold Sore",
        "Warts",
        "Scabies",
        "Athlete's Foot",
        "Dandruff",
        "Seborrhea",
        "Folliculitis",
        "Carbuncle",
        "Keratosis",
        "Ichthyosis",
        "Pemphigoid",
        "Scleroderma",
        "Pemphigus",
        "Erythema",
        "Urticaria",
        "Pityriasis",
        "Molluscum Contagiosum",
        "Kaposi's Sarcoma",
        "Basal Cell Carcinoma",
        "Squamous Cell Carcinoma",
        "Port-wine Stain",
        "Hemangioma",
        "Keloid",
        "Petechiae",
        "Purpura",
        "Telangiectasia",
        "Xeroderma Pigmentosum",
        "Hidradenitis",
        "Hyperhidrosis",
        "Tinea Versicolor",
        "Contact Dermatitis",
        "Psoriatic Arthritis",
        "Alopecia Areata"
      ]
    },
    {
      "id": "types-of-tea",
      "name": "Types of Tea",
      "items": [
        "Green Tea",
        "Black Tea",
        "White Tea",
        "Oolong",
        "Pu-erh",
        "Darjeeling",
        "Earl Grey",
        "English Breakfast",
        "Chamomile",
        "Peppermint",
        "Chrysanthemum",
        "Jasmine",
        "Matcha",
        "Sencha",
        "Gyokuro",
        "Hojicha",
        "Genmaicha",
        "Kukicha",
        "Bancha",
        "Dragon Well",
        "Bi Luo Chun",
        "Tie Guan Yin",
        "Da Hong Pao",
        "Assam",
        "Ceylon",
        "Lapsang Souchong",
        "Keemun",
        "Yunnan",
        "Chai",
        "Rooibos",
        "Hibiscus",
        "Lavender",
        "Lemon Balm",
        "Echinacea",
        "Spearmint",
        "Licorice Root",
        "Rose Hip",
        "Moringa",
        "Nettle",
        "Dandelion",
        "Yerba Mate",
        "Kombucha",
        "Barley Tea",
        "Buckwheat Tea",
        "Thai Tea"
      ]
    },
    {
      "id": "wine-grape-varieties",
      "name": "Wine Grape Varieties",
      "items": [
        "Cabernet Sauvignon",
        "Merlot",
        "Pinot Noir",
        "Syrah",
        "Grenache",
        "Malbec",
        "Zinfandel",
        "Tempranillo",
        "Sangiovese",
        "Nebbiolo",
        "Barbera",
        "Dolcetto",
        "Primitivo",
        "Montepulciano",
        "Aglianico",
        "Nero d'Avola",
        "Chardonnay",
        "Sauvignon Blanc",
        "Riesling",
        "Pinot Grigio",
        "Gewürztraminer",
        "Viognier",
        "Muscat",
        "Albariño",
        "Grüner Veltliner",
        "Torrontés",
        "Vermentino",
        "Fiano",
        "Greco",
        "Falanghina",
        "Roussanne",
        "Marsanne",
        "Chenin Blanc",
        "Sémillon",
        "Pinot Blanc",
        "Carménère",
        "Petit Verdot",
        "Cabernet Franc",
        "Mourvèdre",
        "Cinsault",
        "Carignan",
        "Gamay",
        "Petite Sirah",
        "Tannat",
        "Touriga Nacional"
      ]
    },
    {
      "id": "types-of-bread",
      "name": "Types of Bread",
      "items": [
        "Baguette",
        "Sourdough",
        "Ciabatta",
        "Focaccia",
        "Brioche",
        "Croissant",
        "Naan",
        "Pita",
        "Rye Bread",
        "Pumpernickel",
        "Challah",
        "Bagel",
        "English Muffin",
        "Pretzel",
        "Bao",
        "Tortilla",
        "Injera",
        "Lavash",
        "Matzo",
        "Cornbread",
        "Banana Bread",
        "Soda Bread",
        "Breadsticks",
        "Pão de Queijo",
        "Arepa",
        "Chapati",
        "Paratha",
        "Roti",
        "Mantou",
        "Pain de Campagne",
        "Boule",
        "Pullman Loaf",
        "Tiger Bread",
        "Milk Bread",
        "Kaiser Roll",
        "Hoagie Roll",
        "Dinner Roll",
        "Whole Wheat",
        "Multigrain",
        "Gluten-Free Bread",
        "Zucchini Bread",
        "Cranberry Walnut",
        "Olive Bread",
        "Piadina",
        "Bialy"
      ]
    },
    {
      "id": "spices-and-herbs",
      "name": "Spices & Herbs",
      "items": [
        "Cinnamon",
        "Cumin",
        "Turmeric",
        "Paprika",
        "Cayenne",
        "Black Pepper",
        "White Pepper",
        "Cardamom",
        "Cloves",
        "Nutmeg",
        "Mace",
        "Allspice",
        "Coriander",
        "Fennel",
        "Anise",
        "Star Anise",
        "Caraway",
        "Mustard Seed",
        "Fenugreek",
        "Saffron",
        "Sumac",
        "Harissa",
        "Basil",
        "Oregano",
        "Thyme",
        "Rosemary",
        "Sage",
        "Tarragon",
        "Chives",
        "Dill",
        "Parsley",
        "Cilantro",
        "Bay Leaf",
        "Mint",
        "Lemongrass",
        "Galangal",
        "Ginger",
        "Wasabi",
        "Horseradish",
        "Szechuan Pepper",
        "Juniper Berry",
        "Asafoetida",
        "Mahlab",
        "Nigella",
        "Smoked Paprika"
      ]
    },
    {
      "id": "types-of-beer",
      "name": "Types of Beer",
      "items": [
        "IPA",
        "Pale Ale",
        "Stout",
        "Porter",
        "Lager",
        "Pilsner",
        "Wheat Beer",
        "Hefeweizen",
        "Witbier",
        "Saison",
        "Farmhouse Ale",
        "Belgian Tripel",
        "Belgian Dubbel",
        "Belgian Quad",
        "Lambic",
        "Gueuze",
        "Kriek",
        "Berliner Weisse",
        "Gose",
        "Sour Ale",
        "Brown Ale",
        "Amber Ale",
        "Red Ale",
        "Scotch Ale",
        "Barleywine",
        "Imperial Stout",
        "Milk Stout",
        "Oatmeal Stout",
        "Dry Stout",
        "Cream Ale",
        "Kölsch",
        "Märzen",
        "Bock",
        "Doppelbock",
        "Eisbock",
        "Dunkel",
        "Schwarzbier",
        "Rauchbier",
        "Altbier",
        "Vienna Lager",
        "Helles",
        "Blonde Ale",
        "Session IPA",
        "Double IPA",
        "Triple IPA"
      ]
    },
    {
      "id": "ice-cream-flavors",
      "name": "Ice Cream Flavors",
      "items": [
        "Vanilla",
        "Chocolate",
        "Strawberry",
        "Mint Chocolate Chip",
        "Rocky Road",
        "Cookies and Cream",
        "Butter Pecan",
        "Cookie Dough",
        "Neapolitan",
        "Birthday Cake",
        "Pistachio",
        "Coffee",
        "Caramel",
        "Salted Caramel",
        "Cherry Garcia",
        "Chunky Monkey",
        "Half Baked",
        "Banana",
        "Mango",
        "Coconut",
        "Pineapple",
        "Lemon Sorbet",
        "Orange Sherbet",
        "Rainbow Sherbet",
        "Raspberry",
        "Blueberry",
        "Peach",
        "Peanut Butter Cup",
        "S'mores",
        "Cheesecake",
        "Red Velvet",
        "Black Raspberry",
        "Tiger Tail",
        "Superman",
        "Moose Tracks",
        "Bubble Gum",
        "Cotton Candy",
        "Lavender Honey",
        "Maple Walnut",
        "Ube",
        "Black Sesame",
        "Dulce de Leche",
        "Pralines and Cream",
        "Spumoni",
        "Rum Raisin"
      ]
    },
    {
      "id": "cuts-of-meat",
      "name": "Cuts of Meat",
      "items": [
        "Ribeye",
        "New York Strip",
        "T-Bone",
        "Porterhouse",
        "Filet Mignon",
        "Sirloin",
        "Flank",
        "Skirt",
        "Hanger",
        "Flat Iron",
        "Chuck",
        "Brisket",
        "Short Rib",
        "Oxtail",
        "Tenderloin",
        "Round",
        "Rump",
        "Tri-Tip",
        "Picanha",
        "Bavette",
        "Rack of Lamb",
        "Lamb Chop",
        "Lamb Shoulder",
        "Leg of Lamb",
        "Lamb Shank",
        "Pork Chop",
        "Pork Tenderloin",
        "Pork Shoulder",
        "Pork Belly",
        "Baby Back Ribs",
        "Spare Ribs",
        "Ham",
        "Pancetta",
        "Bacon",
        "Jowl",
        "Chicken Breast",
        "Chicken Thigh",
        "Chicken Wing",
        "Chicken Drumstick",
        "Duck Breast",
        "Veal Cutlet",
        "Osso Buco",
        "Sweetbreads",
        "Tripe",
        "Bone-In Rib Roast"
      ]
    },
    {
      "id": "classical-composers",
      "name": "Classical Composers",
      "items": [
        "Bach",
        "Beethoven",
        "Mozart",
        "Brahms",
        "Tchaikovsky",
        "Chopin",
        "Liszt",
        "Schubert",
        "Haydn",
        "Handel",
        "Vivaldi",
        "Monteverdi",
        "Purcell",
        "Telemann",
        "Rameau",
        "Gluck",
        "Boccherini",
        "Corelli",
        "Tartini",
        "Albinoni",
        "Schumann",
        "Mendelssohn",
        "Berlioz",
        "Wagner",
        "Verdi",
        "Puccini",
        "Donizetti",
        "Bellini",
        "Rossini",
        "Bizet",
        "Gounod",
        "Offenbach",
        "Saint-Saëns",
        "Massenet",
        "Fauré",
        "Debussy",
        "Ravel",
        "Satie",
        "Franck",
        "Bruckner",
        "Mahler",
        "Dvořák",
        "Smetana",
        "Grieg",
        "Sibelius"
      ]
    },
    {
      "id": "dances",
      "name": "Dances",
      "items": [
        "Waltz",
        "Tango",
        "Foxtrot",
        "Quickstep",
        "Viennese Waltz",
        "Salsa",
        "Cha-cha",
        "Rumba",
        "Samba",
        "Paso Doble",
        "Jive",
        "Swing",
        "Lindy Hop",
        "Charleston",
        "Tap",
        "Ballet",
        "Contemporary",
        "Jazz Dance",
        "Hip Hop",
        "Breakdance",
        "Flamenco",
        "Bolero",
        "Fandango",
        "Bhangra",
        "Kathak",
        "Bharatanatyam",
        "Belly Dance",
        "Hula",
        "Lambada",
        "Polka",
        "Mazurka",
        "Csárdás",
        "Highland Fling",
        "Riverdance",
        "Merengue",
        "Bachata",
        "Cumbia",
        "Reggaeton",
        "Krump",
        "Voguing",
        "Moonwalk",
        "Electric Slide",
        "Macarena",
        "Gangnam Style",
        "Country Line Dance"
      ]
    },
    {
      "id": "shakespeare-plays",
      "name": "Shakespeare Plays",
      "items": [
        "Hamlet",
        "Macbeth",
        "Othello",
        "King Lear",
        "Romeo and Juliet",
        "A Midsummer Night's Dream",
        "The Tempest",
        "Twelfth Night",
        "Much Ado About Nothing",
        "As You Like It",
        "The Merchant of Venice",
        "Julius Caesar",
        "Antony and Cleopatra",
        "Richard III",
        "Richard II",
        "Henry V",
        "Henry IV Part 1",
        "Henry IV Part 2",
        "Henry VI Part 1",
        "Henry VI Part 2",
        "Henry VI Part 3",
        "Henry VIII",
        "The Taming of the Shrew",
        "The Comedy of Errors",
        "The Merry Wives of Windsor",
        "Measure for Measure",
        "Love's Labour's Lost",
        "The Winter's Tale",
        "Cymbeline",
        "Pericles",
        "Troilus and Cressida",
        "Timon of Athens",
        "Titus Andronicus",
        "Coriolanus",
        "King John",
        "The Two Gentlemen of Verona",
        "All's Well That Ends Well",
        "The Two Noble Kinsmen",
        "Edward III",
        "Sir Thomas More",
        "Cardenio",
        "A Yorkshire Tragedy",
        "The London Prodigal",
        "Arden of Faversham",
        "Locrine"
      ]
    },
    {
      "id": "ballet-titles",
      "name": "Ballet Titles",
      "items": [
        "Swan Lake",
        "The Nutcracker",
        "Sleeping Beauty",
        "Giselle",
        "Coppélia",
        "La Bayadère",
        "Don Quixote",
        "Onegin",
        "Cinderella",
        "The Firebird",
        "Petrushka",
        "The Rite of Spring",
        "Scheherazade",
        "Spectre of the Rose",
        "Les Sylphides",
        "Sylvia",
        "La Fille Mal Gardée",
        "Paquita",
        "Le Corsaire",
        "Esmeralda",
        "Raymonda",
        "Spartacus",
        "The Prodigal Son",
        "Agon",
        "Napoli",
        "Jewels",
        "Serenade",
        "Concerto Barocco",
        "Fancy Free",
        "Interplay",
        "Rodeo",
        "Billy the Kid",
        "Fall River Legend",
        "Revelations",
        "Appalachian Spring",
        "La Sylphide",
        "La Valse",
        "Afternoon of a Faun",
        "Daphnis and Chloé",
        "The Three-Cornered Hat",
        "Études",
        "Theme and Variations",
        "The Stone Flower",
        "Ivan the Terrible",
        "Manon"
      ]
    },
    {
      "id": "art-movements",
      "name": "Art Movements",
      "items": [
        "Renaissance",
        "Baroque",
        "Rococo",
        "Neoclassicism",
        "Romanticism",
        "Realism",
        "Impressionism",
        "Post-Impressionism",
        "Symbolism",
        "Art Nouveau",
        "Fauvism",
        "Expressionism",
        "Cubism",
        "Futurism",
        "Dadaism",
        "Surrealism",
        "Abstract Expressionism",
        "Pop Art",
        "Minimalism",
        "Conceptual Art",
        "Fluxus",
        "Arte Povera",
        "Land Art",
        "Performance Art",
        "Installation Art",
        "Street Art",
        "Photorealism",
        "Hyperrealism",
        "Neo-Expressionism",
        "Gothic",
        "Mannerism",
        "Constructivism",
        "Suprematism",
        "De Stijl",
        "Bauhaus",
        "Social Realism",
        "Socialist Realism",
        "Ashcan School",
        "Hudson River School",
        "Pre-Raphaelite",
        "Transavantgarde",
        "Young British Artists",
        "Digital Art",
        "Bio Art",
        "Orphism"
      ]
    },
    {
      "id": "roman-emperors",
      "name": "Roman Emperors",
      "items": [
        "Augustus",
        "Tiberius",
        "Caligula",
        "Claudius",
        "Nero",
        "Galba",
        "Otho",
        "Vitellius",
        "Vespasian",
        "Titus",
        "Domitian",
        "Nerva",
        "Trajan",
        "Hadrian",
        "Antoninus Pius",
        "Marcus Aurelius",
        "Commodus",
        "Pertinax",
        "Septimius Severus",
        "Caracalla",
        "Elagabalus",
        "Alexander Severus",
        "Maximinus Thrax",
        "Gordian III",
        "Philip the Arab",
        "Decius",
        "Valerian",
        "Gallienus",
        "Claudius II",
        "Aurelian",
        "Probus",
        "Diocletian",
        "Constantine I",
        "Constantine II",
        "Constantius II",
        "Julian",
        "Jovian",
        "Valentinian I",
        "Valens",
        "Gratian",
        "Theodosius I",
        "Honorius",
        "Arcadius",
        "Romulus Augustulus",
        "Justinian I"
      ]
    },
    {
      "id": "egyptian-pharaohs",
      "name": "Egyptian Pharaohs",
      "items": [
        "Narmer",
        "Djer",
        "Den",
        "Djoser",
        "Sneferu",
        "Khufu",
        "Khafre",
        "Menkaure",
        "Userkaf",
        "Sahure",
        "Unas",
        "Teti",
        "Pepi I",
        "Pepi II",
        "Mentuhotep II",
        "Amenemhat I",
        "Senusret I",
        "Senusret III",
        "Amenemhat III",
        "Ahmose I",
        "Thutmose I",
        "Thutmose II",
        "Hatshepsut",
        "Thutmose III",
        "Amenhotep II",
        "Thutmose IV",
        "Amenhotep III",
        "Akhenaten",
        "Tutankhamun",
        "Ay",
        "Horemheb",
        "Ramesses I",
        "Seti I",
        "Ramesses II",
        "Merneptah",
        "Ramesses III",
        "Ramesses XI",
        "Shoshenq I",
        "Taharqa",
        "Necho II",
        "Apries",
        "Amasis II",
        "Psamtik I",
        "Cleopatra VII",
        "Ptolemy I"
      ]
    },
    {
      "id": "greek-mythology-figures",
      "name": "Greek Mythology Figures",
      "items": [
        "Zeus",
        "Hera",
        "Poseidon",
        "Demeter",
        "Athena",
        "Psyche",
        "Artemis",
        "Ares",
        "Aphrodite",
        "Hephaestus",
        "Hermes",
        "Dionysus",
        "Hades",
        "Persephone",
        "Hestia",
        "Eros",
        "Nike",
        "Iris",
        "Hypnos",
        "Thanatos",
        "Helios",
        "Selene",
        "Eos",
        "Bellerophon",
        "Achilles",
        "Odysseus",
        "Theseus",
        "Atalanta",
        "Jason",
        "Orpheus",
        "Oedipus",
        "Agamemnon",
        "Medea",
        "Circe",
        "Medusa",
        "Minotaur",
        "Sphinx",
        "Cyclops",
        "Scylla",
        "Cerberus",
        "Charon",
        "Prometheus",
        "Icarus",
        "Daedalus",
        "Midas"
      ]
    },
    {
      "id": "nobel-prize-winners",
      "name": "Nobel Prize Winners",
      "items": [
        "Marie Curie",
        "Albert Einstein",
        "Niels Bohr",
        "Max Planck",
        "Werner Heisenberg",
        "Erwin Schrödinger",
        "Paul Dirac",
        "Enrico Fermi",
        "Richard Feynman",
        "Murray Gell-Mann",
        "Ernest Rutherford",
        "Linus Pauling",
        "Francis Crick",
        "James Watson",
        "Frederick Sanger",
        "Alexander Fleming",
        "Ivan Pavlov",
        "Albert Schweitzer",
        "Mother Teresa",
        "Martin Luther King Jr.",
        "Elie Wiesel",
        "Nelson Mandela",
        "Malala Yousafzai",
        "Barack Obama",
        "Ernest Hemingway",
        "William Faulkner",
        "Gabriel García Márquez",
        "Toni Morrison",
        "Pablo Neruda",
        "Samuel Beckett",
        "Albert Camus",
        "Boris Pasternak",
        "Rabindranath Tagore",
        "Doris Lessing",
        "Alice Munro",
        "Svetlana Alexievich",
        "Aung San Suu Kyi",
        "Wangari Maathai",
        "Milton Friedman",
        "Amartya Sen",
        "Friedrich Hayek",
        "John Steinbeck",
        "Bertrand Russell",
        "Winston Churchill",
        "Woodrow Wilson"
      ]
    },
    {
      "id": "cat-breeds",
      "name": "Cat Breeds",
      "items": [
        "Persian",
        "Maine Coon",
        "Siamese",
        "Ragdoll",
        "Bengal",
        "British Shorthair",
        "American Shorthair",
        "Sphynx",
        "Scottish Fold",
        "Norwegian Forest",
        "Siberian",
        "Birman",
        "Burmese",
        "Tonkinese",
        "Balinese",
        "Himalayan",
        "Turkish Angora",
        "Turkish Van",
        "Russian Blue",
        "Chartreux",
        "Abyssinian",
        "Somali",
        "Ocicat",
        "Egyptian Mau",
        "Bombay",
        "Devon Rex",
        "Cornish Rex",
        "Selkirk Rex",
        "LaPerm",
        "American Curl",
        "Manx",
        "Ragamuffin",
        "Savannah",
        "Lykoi",
        "Peterbald",
        "Korat",
        "Singapura",
        "Havana Brown",
        "Munchkin",
        "American Bobtail",
        "Exotic Shorthair",
        "Burmilla",
        "Chausie",
        "Pixie-Bob",
        "Scottish Straight"
      ]
    },
    {
      "id": "freshwater-fish",
      "name": "Freshwater Fish",
      "items": [
        "Largemouth Bass",
        "Smallmouth Bass",
        "Bluegill",
        "Crappie",
        "Walleye",
        "Pike",
        "Muskellunge",
        "Yellow Perch",
        "Catfish",
        "Channel Catfish",
        "Flathead Catfish",
        "Blue Catfish",
        "Rainbow Trout",
        "Brown Trout",
        "Brook Trout",
        "Lake Trout",
        "Steelhead",
        "Chinook Salmon",
        "Coho Salmon",
        "Atlantic Salmon",
        "Carp",
        "Goldfish",
        "Koi",
        "Tilapia",
        "Sunfish",
        "Pumpkinseed",
        "Rock Bass",
        "Drum",
        "Sturgeon",
        "Paddlefish",
        "Gar",
        "Bowfin",
        "Burbot",
        "Cisco",
        "Whitefish",
        "Grayling",
        "Arctic Char",
        "Minnow",
        "Chub",
        "Shad",
        "Roach",
        "Bream",
        "Tench",
        "Zander",
        "Perch"
      ]
    },
    {
      "id": "butterfly-moth-species",
      "name": "Butterfly / Moth Species",
      "items": [
        "Monarch",
        "Swallowtail",
        "Painted Lady",
        "Red Admiral",
        "Cabbage White",
        "Comma",
        "Peacock",
        "Small Tortoiseshell",
        "Orange Tip",
        "Brimstone",
        "Clouded Yellow",
        "Holly Blue",
        "Common Blue",
        "Adonis Blue",
        "Chalkhill Blue",
        "Large White",
        "Marbled White",
        "Ringlet",
        "Meadow Brown",
        "Gatekeeper",
        "Speckled Wood",
        "Wall Brown",
        "Large Heath",
        "Purple Emperor",
        "White Admiral",
        "Hairstreak",
        "Skipper",
        "Atlas Moth",
        "Luna Moth",
        "Cecropia Moth",
        "Polyphemus Moth",
        "Io Moth",
        "Deaths Head Hawk-Moth",
        "Elephant Hawk-Moth",
        "Hummingbird Hawk-Moth",
        "Cinnabar Moth",
        "Garden Tiger Moth",
        "Six-spot Burnet",
        "Emperor Moth",
        "Peppered Moth",
        "Oak Eggar",
        "Silk Moth",
        "Madagascan Sunset Moth",
        "Glasswing Butterfly",
        "Blue Morpho"
      ]
    },
    {
      "id": "shark-species",
      "name": "Shark Species",
      "items": [
        "Great White",
        "Hammerhead",
        "Tiger",
        "Bull",
        "Whale",
        "Nurse",
        "Lemon",
        "Blue",
        "Mako",
        "Thresher",
        "Blacktip Reef",
        "Whitetip Reef",
        "Oceanic Whitetip",
        "Sandbar",
        "Sand Tiger",
        "Grey Reef",
        "Silvertip",
        "Caribbean Reef",
        "Zebra",
        "Leopard",
        "Horn",
        "Port Jackson",
        "Wobbegong",
        "Angel",
        "Goblin",
        "Cookiecutter",
        "Megamouth",
        "Basking",
        "Tope",
        "Bramble",
        "Frilled",
        "Tawny Nurse",
        "Epaulette",
        "Bamboo",
        "Catshark",
        "Swell Shark",
        "Pyjama",
        "Scalloped Hammerhead",
        "Great Hammerhead",
        "Bonnethead",
        "Spiny Dogfish",
        "Smooth Dogfish",
        "Dusky",
        "Spinner",
        "Silky"
      ]
    },
    {
      "id": "martial-arts-styles",
      "name": "Martial Arts Styles",
      "items": [
        "Karate",
        "Judo",
        "Taekwondo",
        "Jiu-Jitsu",
        "Brazilian Jiu-Jitsu",
        "Kung Fu",
        "Wing Chun",
        "Tai Chi",
        "Wushu",
        "Muay Thai",
        "Kickboxing",
        "Boxing",
        "Wrestling",
        "Sambo",
        "Krav Maga",
        "Hapkido",
        "Aikido",
        "Jeet Kune Do",
        "Capoeira",
        "Silat",
        "Arnis",
        "Savate",
        "Pankration",
        "Sumo",
        "Ninjutsu",
        "Iaido",
        "Kendo",
        "Kyudo",
        "Naginata",
        "Baguazhang",
        "Xingyiquan",
        "Bajiquan",
        "Praying Mantis",
        "Drunken Boxing",
        "Tang Soo Do",
        "Hwa Rang Do",
        "Ssireum",
        "Bokator",
        "Lethwei",
        "Vovinam",
        "Vale Tudo",
        "Systema",
        "Kalaripayattu",
        "Dambe",
        "Catch Wrestling"
      ]
    },
    {
      "id": "video-game-franchises",
      "name": "Video Game Franchises",
      "items": [
        "Super Mario",
        "The Legend of Zelda",
        "Pokémon",
        "Metroid",
        "Donkey Kong",
        "Kirby",
        "Star Fox",
        "Fire Emblem",
        "Animal Crossing",
        "Splatoon",
        "Halo",
        "Gears of War",
        "Forza",
        "Minecraft",
        "The Elder Scrolls",
        "Fallout",
        "DOOM",
        "Half-Life",
        "Portal",
        "Counter-Strike",
        "Grand Theft Auto",
        "Red Dead Redemption",
        "Call of Duty",
        "Assassin's Creed",
        "Far Cry",
        "Battlefield",
        "Need for Speed",
        "The Sims",
        "Mass Effect",
        "Dragon Age",
        "FIFA",
        "Madden",
        "NBA 2K",
        "Street Fighter",
        "Mortal Kombat",
        "Tekken",
        "Resident Evil",
        "Silent Hill",
        "Final Fantasy",
        "Dark Souls",
        "Sonic",
        "Mega Man",
        "Castlevania",
        "Metal Gear",
        "Pac-Man"
      ]
    },
    {
      "id": "rhetorical-devices",
      "name": "Rhetorical Devices",
      "items": [
        "Metaphor",
        "Simile",
        "Alliteration",
        "Anaphora",
        "Assonance",
        "Consonance",
        "Onomatopoeia",
        "Hyperbole",
        "Understatement",
        "Irony",
        "Sarcasm",
        "Paradox",
        "Oxymoron",
        "Antithesis",
        "Chiasmus",
        "Parallelism",
        "Epistrophe",
        "Symploce",
        "Anadiplosis",
        "Polysyndeton",
        "Asyndeton",
        "Apophasis",
        "Rhetorical Question",
        "Personification",
        "Allegory",
        "Metonymy",
        "Synecdoche",
        "Euphemism",
        "Dysphemism",
        "Litotes",
        "Amplification",
        "Climax",
        "Anticlimax",
        "Anecdote",
        "Analogy",
        "Pathos",
        "Ethos",
        "Logos",
        "Kairos",
        "Zeugma",
        "Epiphora",
        "Apostrophe",
        "Allusion",
        "Antanaclasis",
        "Anastrophe"
      ]
    },
    {
      "id": "loanwords-in-english",
      "name": "Loanwords in English",
      "items": [
        "Schadenfreude",
        "Déjà Vu",
        "Café",
        "Restaurant",
        "Silhouette",
        "Genre",
        "Entrepreneur",
        "Bureaucracy",
        "Avant-Garde",
        "Carte Blanche",
        "Cliché",
        "Faux Pas",
        "Joie de Vivre",
        "Rendezvous",
        "Charade",
        "Chic",
        "Naïve",
        "Paparazzi",
        "Graffiti",
        "Umbrella",
        "Piano",
        "Ciao",
        "Fiasco",
        "Ghetto",
        "Influenza",
        "Replica",
        "Vendetta",
        "Crescendo",
        "Tempo",
        "Kindergarten",
        "Angst",
        "Kaput",
        "Wanderlust",
        "Zeitgeist",
        "Leitmotif",
        "Poltergeist",
        "Karaoke",
        "Tsunami",
        "Tycoon",
        "Sushi",
        "Bonsai",
        "Voodoo",
        "Tattoo",
        "Ketchup",
        "Algebra"
      ]
    },
    {
      "id": "english-idioms",
      "name": "English Idioms",
      "items": [
        "Break a leg",
        "Bite the bullet",
        "Hit the nail on the head",
        "Under the weather",
        "Piece of cake",
        "Let the cat out of the bag",
        "Cost an arm and a leg",
        "Once in a blue moon",
        "The ball is in your court",
        "Burn bridges",
        "Kill two birds with one stone",
        "Spill the beans",
        "Barking up the wrong tree",
        "Beat around the bush",
        "Bite the dust",
        "Blow off steam",
        "Break the ice",
        "Cut corners",
        "Hit the sack",
        "Miss the boat",
        "No pain no gain",
        "On the fence",
        "Pull someone's leg",
        "Raining cats and dogs",
        "Rock the boat",
        "See eye to eye",
        "Speak of the devil",
        "The best of both worlds",
        "The elephant in the room",
        "The tip of the iceberg",
        "Throw in the towel",
        "Up in the air",
        "Wet behind the ears",
        "Back to the drawing board",
        "A blessing in disguise",
        "Burn the midnight oil",
        "Can't see the forest for the trees",
        "Don't judge a book by its cover",
        "Hit the road",
        "Keep your chin up",
        "Sit on the fence",
        "A dime a dozen",
        "Bite off more than you can chew",
        "Get a taste of your own medicine",
        "Let sleeping dogs lie"
      ]
    },
    {
      "id": "currencies-of-the-world",
      "name": "Currencies of the World",
      "items": [
        "US Dollar",
        "Euro",
        "British Pound",
        "Yen",
        "Franc",
        "Canadian Dollar",
        "Australian Dollar",
        "Yuan",
        "Indian Rupee",
        "Won",
        "Hong Kong Dollar",
        "Singapore Dollar",
        "New Zealand Dollar",
        "Krona",
        "Norwegian Krone",
        "Danish Krone",
        "Koruna",
        "Złoty",
        "Forint",
        "Leu",
        "Ruble",
        "Lira",
        "Shekel",
        "Saudi Riyal",
        "Dirham",
        "Qatari Riyal",
        "Kuwaiti Dinar",
        "Bahraini Dinar",
        "Egyptian Pound",
        "Rand",
        "Naira",
        "Shilling",
        "Cedi",
        "Real",
        "Argentine Peso",
        "Chilean Peso",
        "Colombian Peso",
        "Mexican Peso",
        "Sol",
        "Baht",
        "Rupiah",
        "Ringgit",
        "Philippine Peso",
        "Pakistani Rupee",
        "Taka"
      ]
    },
    {
      "id": "fonts-and-typefaces",
      "name": "Fonts & Typefaces",
      "items": [
        "Helvetica",
        "Arial",
        "Times New Roman",
        "Georgia",
        "Garamond",
        "Baskerville",
        "Futura",
        "Gill Sans",
        "Univers",
        "Frutiger",
        "Bodoni",
        "Didot",
        "Caslon",
        "Palatino",
        "Optima",
        "Rockwell",
        "Clarendon",
        "Century Gothic",
        "Trebuchet MS",
        "Verdana",
        "Tahoma",
        "Comic Sans",
        "Impact",
        "Copperplate",
        "Avenir",
        "Eurostile",
        "Myriad",
        "Calibri",
        "Cambria",
        "Consolas",
        "Courier New",
        "Inconsolata",
        "Source Code Pro",
        "Roboto",
        "Lato",
        "Open Sans",
        "Montserrat",
        "Raleway",
        "Playfair Display",
        "Merriweather",
        "Oswald",
        "Ubuntu",
        "Nunito",
        "Josefin Sans",
        "Bebas Neue"
      ]
    },
    {
      "id": "candy-and-sweets",
      "name": "Candy & Sweets",
      "items": [
        "Snickers",
        "Kit Kat",
        "Reese's Peanut Butter Cups",
        "M&Ms",
        "Twix",
        "Milky Way",
        "3 Musketeers",
        "Butterfinger",
        "Baby Ruth",
        "Almond Joy",
        "Mounds",
        "Hershey Bar",
        "Hershey Kisses",
        "Toblerone",
        "Ferrero Rocher",
        "Kinder Bueno",
        "Skittles",
        "Starburst",
        "Jolly Rancher",
        "Nerds",
        "Sour Patch Kids",
        "Gummy Bears",
        "Gummy Worms",
        "Peach Rings",
        "Swedish Fish",
        "Twizzlers",
        "Red Vines",
        "Mike and Ike",
        "Jelly Belly",
        "Pop Rocks",
        "Fun Dip",
        "Pixy Stix",
        "Candy Corn",
        "Lemonheads",
        "Warheads",
        "Airheads",
        "Ring Pop",
        "Now and Later",
        "Sweet Tarts",
        "Gobstopper",
        "Laffy Taffy",
        "Tootsie Roll",
        "York Peppermint Pattie",
        "Crunch Bar",
        "Nestle Crunch"
      ]
    },
    {
      "id": "cereals",
      "name": "Cereals",
      "items": [
        "Corn Flakes",
        "Frosted Flakes",
        "Rice Krispies",
        "Cheerios",
        "Honey Nut Cheerios",
        "Froot Loops",
        "Lucky Charms",
        "Cap'n Crunch",
        "Cocoa Puffs",
        "Count Chocula",
        "Trix",
        "Frosted Mini-Wheats",
        "Wheaties",
        "Special K",
        "Raisin Bran",
        "Grape Nuts",
        "All-Bran",
        "Shredded Wheat",
        "Fruity Pebbles",
        "Kix",
        "Apple Jacks",
        "Honey Smacks",
        "Cookie Crisp",
        "Golden Grahams",
        "Cinnamon Toast Crunch",
        "French Toast Crunch",
        "Reese's Puffs",
        "Cocoa Krispies",
        "Corn Pops",
        "Honey Bunches of Oats",
        "Cracklin' Oat Bran",
        "Total",
        "Basic 4",
        "Muesli",
        "Granola",
        "Oatmeal Crisp",
        "Corn Chex",
        "Rice Chex",
        "Wheat Chex",
        "Multi-Bran Chex",
        "Waffle Crisp",
        "Berry Berry Kix",
        "Peanut Butter Cap'n Crunch",
        "Cinnamon Life",
        "Honey Graham Oh!s"
      ]
    },
    {
      "id": "types-of-knots",
      "name": "Types of Knots",
      "items": [
        "Square",
        "Bowline",
        "Clove Hitch",
        "Reef Knot",
        "Sheet Bend",
        "Cleat Hitch",
        "Figure Eight",
        "Overhand",
        "Half Hitch",
        "Two Half Hitches",
        "Rolling Hitch",
        "Timber Hitch",
        "Anchor Hitch",
        "Fisherman's",
        "Double Fisherman's",
        "Blood",
        "Surgeon's",
        "Palomar",
        "Uni Knot",
        "Albright",
        "Prusik",
        "Munter Hitch",
        "Klemheist",
        "Alpine Butterfly",
        "Trucker's Hitch",
        "Marlinspike Hitch",
        "Turk's Head",
        "Monkey's Fist",
        "Slip",
        "Noose",
        "Constrictor",
        "Boa",
        "Transom",
        "Lark's Head",
        "Cow Hitch",
        "Girth Hitch",
        "Water",
        "Ring Bend",
        "Tape",
        "Hunter's Bend",
        "Zeppelin Bend",
        "Ashley Stopper",
        "Chinese Button Knot",
        "Carrick Bend",
        "Diamond"
      ]
    },
    {
      "id": "simpsons-characters",
      "name": "Simpsons Characters",
      "items": [
        "Homer Simpson",
        "Marge Simpson",
        "Bart Simpson",
        "Lisa Simpson",
        "Maggie Simpson",
        "Montgomery Burns",
        "Waylon Smithers",
        "Ned Flanders",
        "Maude Flanders",
        "Rod Flanders",
        "Todd Flanders",
        "Moe Szyslak",
        "Barney Gumble",
        "Chief Clancy Wiggum",
        "Ralph Wiggum",
        "Apu Nahasapeemapetilon",
        "Krusty the Clown",
        "Sideshow Bob",
        "Sideshow Mel",
        "Milhouse Van Houten",
        "Nelson Muntz",
        "Martin Prince",
        "Database",
        "Groundskeeper Willie",
        "Principal Skinner",
        "Superintendent Chalmers",
        "Edna Krabappel",
        "Otto Mann",
        "Comic Book Guy",
        "Hans Moleman",
        "Disco Stu",
        "Professor Frink",
        "Dr. Nick Riviera",
        "Dr. Julius Hibbert",
        "Lionel Hutz",
        "Troy McClure",
        "Kent Brockman",
        "Reverend Lovejoy",
        "Patty Bouvier",
        "Selma Bouvier",
        "Snake Jailbird",
        "Fat Tony",
        "Lenny Leonard",
        "Carl Carlson",
        "Itchy & Scratchy"
      ]
    },
    {
      "id": "sitcoms",
      "name": "Sitcoms",
      "items": [
        "I Love Lucy",
        "The Dick Van Dyke Show",
        "The Mary Tyler Moore Show",
        "All in the Family",
        "M*A*S*H",
        "Cheers",
        "Seinfeld",
        "Friends",
        "Frasier",
        "The Office",
        "Parks and Recreation",
        "30 Rock",
        "Arrested Development",
        "Community",
        "It's Always Sunny in Philadelphia",
        "The Big Bang Theory",
        "How I Met Your Mother",
        "Brooklyn Nine-Nine",
        "Schitt's Creek",
        "Abbott Elementary",
        "Curb Your Enthusiasm",
        "Two and a Half Men",
        "Everybody Loves Raymond",
        "King of Queens",
        "Malcolm in the Middle",
        "That '70s Show",
        "Home Improvement",
        "Golden Girls",
        "Designing Women",
        "Roseanne",
        "Murphy Brown",
        "NewsRadio",
        "Will & Grace",
        "Scrubs",
        "Modern Family",
        "Married with Children",
        "Superstore",
        "New Girl",
        "Entourage",
        "Family Ties",
        "Growing Pains",
        "Perfect Strangers",
        "Dharma & Greg",
        "Just Shoot Me",
        "Taxi"
      ]
    },
    {
      "id": "board-games",
      "name": "Board Games",
      "items": [
        "Monopoly",
        "Scrabble",
        "Chess",
        "Checkers",
        "Clue",
        "Risk",
        "Battleship",
        "Operation",
        "Candy Land",
        "Chutes and Ladders",
        "Sorry!",
        "Scattergories",
        "Parcheesi",
        "Backgammon",
        "Mahjong",
        "Go",
        "Stratego",
        "Connect Four",
        "Jenga",
        "Trivial Pursuit",
        "Pictionary",
        "Taboo",
        "Cranium",
        "Balderdash",
        "Boggle",
        "Bananagrams",
        "Apples to Apples",
        "Pandemic",
        "Ticket to Ride",
        "Catan",
        "Agricola",
        "Carcassonne",
        "Dominion",
        "7 Wonders",
        "Coup",
        "Codenames",
        "Dixit",
        "Mysterium",
        "Azul",
        "Wingspan",
        "Everdell",
        "Gloomhaven",
        "Spirit Island",
        "Terraforming Mars",
        "Betrayal at House on the Hill"
      ]
    }
  ]
}